topsis_py/topsis.py
topsis_abhimat_101983058-1.0.3.dist-info/LICENSE
topsis_abhimat_101983058-1.0.3.dist-info/METADATA
topsis_abhimat_101983058-1.0.3.dist-info/WHEEL
topsis_abhimat_101983058-1.0.3.dist-info/entry_points.txt
topsis_abhimat_101983058-1.0.3.dist-info/top_level.txt
topsis_abhimat_101983058-1.0.3.dist-info/RECORD
