Metadata-Version: 2.1
Name: topsis-abhimat-101983058
Version: 1.0.3
Summary: A Python package implementing TOPSIS technique.
Home-page: https://github.com/abhi0444/topsis
Author: Abhimat Gupta
Author-email: abhimatg0004@gmail.com
License: MIT
Keywords: Ranking,Topsis
Platform: UNKNOWN
Classifier: License :: OSI Approved :: MIT License
Classifier: Programming Language :: Python :: 3.7
Requires-Dist: scipy
Requires-Dist: numpy
Requires-Dist: pandas
